[{"id":"3310062001","district_id":"3310062","postal_code":"57467","name":"Karangpakel"},{"id":"3310062002","district_id":"3310062","postal_code":"57467","name":"Wanglu"},{"id":"3310062003","district_id":"3310062","postal_code":"57467","name":"Trucuk"},{"id":"3310062004","district_id":"3310062","postal_code":"57467","name":"Kalikebo"},{"id":"3310062005","district_id":"3310062","postal_code":"57467","name":"Gaden"},{"id":"3310062006","district_id":"3310062","postal_code":"57467","name":"Planggu"},{"id":"3310062007","district_id":"3310062","postal_code":"57467","name":"Pundungsari"},{"id":"3310062008","district_id":"3310062","postal_code":"57467","name":"Sajen"},{"id":"3310062009","district_id":"3310062","postal_code":"57467","name":"Puluhan"},{"id":"3310062010","district_id":"3310062","postal_code":"57467","name":"Kradenan"},{"id":"3310062011","district_id":"3310062","postal_code":"57467","name":"Sabranglor"},{"id":"3310062012","district_id":"3310062","postal_code":"57467","name":"Jatipuro"},{"id":"3310062013","district_id":"3310062","postal_code":"57473","name":"Wonosari"},{"id":"3310062014","district_id":"3310062","postal_code":"57467","name":"Mireng"},{"id":"3310062015","district_id":"3310062","postal_code":"57467","name":"Bero"},{"id":"3310062016","district_id":"3310062","postal_code":"57467","name":"Mandong"},{"id":"3310062017","district_id":"3310062","postal_code":"57467","name":"Sumber"},{"id":"3310062018","district_id":"3310062","postal_code":"57467","name":"Palar"}]