[{"id":"3506082001","district_id":"3506082","postal_code":"64292","name":"Puncu"},{"id":"3506082002","district_id":"3506082","postal_code":"64292","name":"Asmorobangun"},{"id":"3506082003","district_id":"3506082","postal_code":"64292","name":"Manggis"},{"id":"3506082004","district_id":"3506082","postal_code":"64292","name":"Sidomulyo"},{"id":"3506082005","district_id":"3506082","postal_code":"64292","name":"Watugede"},{"id":"3506082006","district_id":"3506082","postal_code":"64292","name":"Gadungan"},{"id":"3506082007","district_id":"3506082","postal_code":"64292","name":"Wonorejo"},{"id":"3506082008","district_id":"3506082","postal_code":"64292","name":"Satak"}]