[{"id":"5203172001","district_id":"5203172","postal_code":"83616","name":"Labuhan Haji"},{"id":"5203172002","district_id":"5203172","postal_code":"83617","name":"Peneda Gandor"},{"id":"5203172003","district_id":"5203172","postal_code":"83614","name":"Teros"},{"id":"5203172006","district_id":"5203172","postal_code":"83615","name":"Korleko"},{"id":"5203172008","district_id":"5203172","postal_code":"83617","name":"Kertasari"},{"id":"5203172009","district_id":"5203172","postal_code":"83615","name":"Tirtanadi"},{"id":"5203172010","district_id":"5203172","postal_code":"83614","name":"Banjarsari"},{"id":"5203172011","district_id":"5203172","postal_code":"83615","name":"Korleko Selatan"}]