[{"id":"6503062001","district_id":"6503062","postal_code":"77481","name":"Pembeliangan"},{"id":"6503062002","district_id":"6503062","postal_code":"77481","name":"Apas"},{"id":"6503062003","district_id":"6503062","postal_code":"77481","name":"Kunyit"},{"id":"6503062004","district_id":"6503062","postal_code":"77481","name":"Tetaban"},{"id":"6503062005","district_id":"6503062","postal_code":"77481","name":"Kekayap"},{"id":"6503062006","district_id":"6503062","postal_code":"77481","name":"Bebanas"},{"id":"6503062007","district_id":"6503062","postal_code":"77481","name":"Lulu"},{"id":"6503062008","district_id":"6503062","postal_code":"77481","name":"Sujau"},{"id":"6503062009","district_id":"6503062","postal_code":"77481","name":"Melasu Baru"},{"id":"6503062010","district_id":"6503062","postal_code":"77481","name":"Harapan"}]