[{"id":"7324082001","district_id":"7324082","postal_code":"92972","name":"Bayondo"},{"id":"7324082002","district_id":"7324082","postal_code":"92972","name":"Mulyasri"},{"id":"7324082007","district_id":"7324082","postal_code":"92972","name":"Lestari"},{"id":"7324082008","district_id":"7324082","postal_code":"92972","name":"Kalpataru"},{"id":"7324082011","district_id":"7324082","postal_code":"92972","name":"Tadulako"},{"id":"7324082012","district_id":"7324082","postal_code":"92972","name":"Beringin Jaya"},{"id":"7324082015","district_id":"7324082","postal_code":"92972","name":"Bangun Jaya"},{"id":"7324082016","district_id":"7324082","postal_code":"92972","name":"Mandiri"},{"id":"7324082017","district_id":"7324082","postal_code":"92972","name":"Sumber Alam"},{"id":"7324082018","district_id":"7324082","postal_code":"92972","name":"Ujung Baru"},{"id":"7324082019","district_id":"7324082","postal_code":"92972","name":"Bangun Karya"},{"id":"7324082020","district_id":"7324082","postal_code":"92972","name":"Rante Mario"}]