[{"id":"7404282001","district_id":"7404282","postal_code":"93754","name":"Kaumbu"},{"id":"7404282002","district_id":"7404282","postal_code":"93754","name":"Wolowa"},{"id":"7404282003","district_id":"7404282","postal_code":"93754","name":"Matawia"},{"id":"7404282004","district_id":"7404282","postal_code":"93754","name":"Wolowa Baru"},{"id":"7404282005","district_id":"7404282","postal_code":"93754","name":"Suka Maju"},{"id":"7404282006","district_id":"7404282","postal_code":"93754","name":"Bungi"},{"id":"7404282007","district_id":"7404282","postal_code":"93754","name":"Galanti"}]