[{"id":"8201092001","district_id":"8201092","postal_code":"97758","name":"Loce"},{"id":"8201092002","district_id":"8201092","postal_code":"97758","name":"Idam Gamlamo"},{"id":"8201092003","district_id":"8201092","postal_code":"97758","name":"Gamomeng"},{"id":"8201092004","district_id":"8201092","postal_code":"97758","name":"Akelamo"},{"id":"8201092005","district_id":"8201092","postal_code":"97758","name":"Taraudu Kusu"},{"id":"8201092006","district_id":"8201092","postal_code":"97758","name":"Awer"},{"id":"8201092007","district_id":"8201092","postal_code":"97758","name":"Aketola"},{"id":"8201092008","district_id":"8201092","postal_code":"97758","name":"Tibobo"},{"id":"8201092009","district_id":"8201092","postal_code":"97758","name":"Hoku- Hoku Gam"},{"id":"8201092010","district_id":"8201092","postal_code":"97758","name":"Gamiyel"},{"id":"8201092011","district_id":"8201092","postal_code":"97758","name":"Golago Kusuma"},{"id":"8201092012","district_id":"8201092","postal_code":"97758","name":"Ngaon"},{"id":"8201092013","district_id":"8201092","postal_code":"97758","name":"Gamsugi"},{"id":"8201092014","district_id":"8201092","postal_code":"97758","name":"Taba Campaka"},{"id":"8201092015","district_id":"8201092","postal_code":"97758","name":"Campaka"},{"id":"8201092016","district_id":"8201092","postal_code":"97758","name":"Goal"},{"id":"8201092017","district_id":"8201092","postal_code":"97758","name":"Sidodadi"},{"id":"8201092018","district_id":"8201092","postal_code":"97758","name":"Air Panas"}]