[{"id":"8272022001","district_id":"8272022","postal_code":"97827","name":"Kaiyasa"},{"id":"8272022005","district_id":"8272022","postal_code":"97827","name":"Oba"},{"id":"8272022006","district_id":"8272022","postal_code":"97827","name":"Somahode"},{"id":"8272022007","district_id":"8272022","postal_code":"97827","name":"Ake Kolano"},{"id":"8272022009","district_id":"8272022","postal_code":"97827","name":"Balbar"},{"id":"8272022010","district_id":"8272022","postal_code":"97827","name":"Bukit Durian"},{"id":"8272022011","district_id":"8272022","postal_code":"97827","name":"Galala"},{"id":"8272022012","district_id":"8272022","postal_code":"97827","name":"Ampera"},{"id":"8272022013","district_id":"8272022","postal_code":"97827","name":"Kusu"},{"id":"8272022014","district_id":"8272022","postal_code":"97827","name":"Garojou"},{"id":"8272022015","district_id":"8272022","postal_code":"97827","name":"Gosale"}]