[{"id":"9114402001","district_id":"9114402","postal_code":"99014","name":"Wania"},{"id":"9114402002","district_id":"9114402","postal_code":"99014","name":"Milipaa"},{"id":"9114402003","district_id":"9114402","postal_code":"99014","name":"Tarawi"},{"id":"9114402004","district_id":"9114402","postal_code":"99014","name":"Niagale"},{"id":"9114402005","district_id":"9114402","postal_code":"99014","name":"Bumbu"},{"id":"9114402006","district_id":"9114402","postal_code":"99014","name":"Ambena"},{"id":"9114402007","district_id":"9114402","postal_code":"99014","name":"Gunombo"},{"id":"9114402008","district_id":"9114402","postal_code":"99014","name":"Mawi"},{"id":"9114402009","district_id":"9114402","postal_code":"99014","name":"Ripa"},{"id":"9114402010","district_id":"9114402","postal_code":"99014","name":"Delegari"}]