[{"id":"9124202001","district_id":"9124202","postal_code":"99904","name":"Biripem"},{"id":"9124202002","district_id":"9124202","postal_code":"99904","name":"Dakbri"},{"id":"9124202003","district_id":"9124202","postal_code":"99904","name":"Abualak"},{"id":"9124202004","district_id":"9124202","postal_code":"99904","name":"Urugom"},{"id":"9124202005","district_id":"9124202","postal_code":"99904","name":"Area"},{"id":"9124202006","district_id":"9124202","postal_code":"99904","name":"Wumaga"},{"id":"9124202007","district_id":"9124202","postal_code":"99904","name":"Gulama"},{"id":"9124202008","district_id":"9124202","postal_code":"99904","name":"Kigam"}]