[{"id":"1205011","regency_id":"1205","name":"Bahorok"},{"id":"1205012","regency_id":"1205","name":"Bahorok"},{"id":"1205021","regency_id":"1205","name":"Salapian"},{"id":"1205022","regency_id":"1205","name":"Salapian"},{"id":"1205031","regency_id":"1205","name":"Kuala"},{"id":"1205032","regency_id":"1205","name":"Kuala"},{"id":"1205041","regency_id":"1205","name":"Sei Bingei"},{"id":"1205042","regency_id":"1205","name":"Sei Bingei"},{"id":"1205051","regency_id":"1205","name":"Binjai"},{"id":"1205052","regency_id":"1205","name":"Binjai"},{"id":"1205061","regency_id":"1205","name":"Selesai"},{"id":"1205062","regency_id":"1205","name":"Selesai"},{"id":"1205071","regency_id":"1205","name":"Stabat"},{"id":"1205072","regency_id":"1205","name":"Stabat"},{"id":"1205081","regency_id":"1205","name":"Wampu"},{"id":"1205082","regency_id":"1205","name":"Wampu"},{"id":"1205091","regency_id":"1205","name":"Secanggang"},{"id":"1205092","regency_id":"1205","name":"Secanggang"},{"id":"1205101","regency_id":"1205","name":"Hinai"},{"id":"1205102","regency_id":"1205","name":"Hinai"},{"id":"1205111","regency_id":"1205","name":"Tanjung Pura"},{"id":"1205112","regency_id":"1205","name":"Tanjung Pura"},{"id":"1205121","regency_id":"1205","name":"Padang Tualang"},{"id":"1205122","regency_id":"1205","name":"Padang Tualang"},{"id":"1205131","regency_id":"1205","name":"Gebang"},{"id":"1205132","regency_id":"1205","name":"Gebang"},{"id":"1205141","regency_id":"1205","name":"Babalan"},{"id":"1205142","regency_id":"1205","name":"Babalan"},{"id":"1205151","regency_id":"1205","name":"Pangkalan Susu"},{"id":"1205152","regency_id":"1205","name":"Pangkalan Susu"},{"id":"1205161","regency_id":"1205","name":"Besitang"},{"id":"1205162","regency_id":"1205","name":"Besitang"},{"id":"1205171","regency_id":"1205","name":"Sei Lepan"},{"id":"1205172","regency_id":"1205","name":"Sei Lepan"},{"id":"1205181","regency_id":"1205","name":"Berandan Barat"},{"id":"1205182","regency_id":"1205","name":"Berandan Barat"},{"id":"1205191","regency_id":"1205","name":"Batang Serangan"},{"id":"1205192","regency_id":"1205","name":"Batang Serangan"},{"id":"1205201","regency_id":"1205","name":"Sawit Seberang"},{"id":"1205202","regency_id":"1205","name":"Sawit Seberang"},{"id":"1205212","regency_id":"1205","name":"Sirapit"},{"id":"1205222","regency_id":"1205","name":"Kutambaru"},{"id":"1205232","regency_id":"1205","name":"Pematang Jaya"}]