[{"id":"1607011","regency_id":"1607","name":"Banyuasin I"},{"id":"1607012","regency_id":"1607","name":"Banyuasin I"},{"id":"1607022","regency_id":"1607","name":"Banyuasin II"},{"id":"1607031","regency_id":"1607","name":"Banyuasin III"},{"id":"1607032","regency_id":"1607","name":"Banyuasin III"},{"id":"1607042","regency_id":"1607","name":"Pulau Rimau"},{"id":"1607051","regency_id":"1607","name":"Betung"},{"id":"1607052","regency_id":"1607","name":"Betung"},{"id":"1607061","regency_id":"1607","name":"Rambutan"},{"id":"1607062","regency_id":"1607","name":"Rambutan"},{"id":"1607072","regency_id":"1607","name":"Muara Padang"},{"id":"1607082","regency_id":"1607","name":"Muara Telang"},{"id":"1607091","regency_id":"1607","name":"Makarti Jaya"},{"id":"1607092","regency_id":"1607","name":"Makarti Jaya"},{"id":"1607101","regency_id":"1607","name":"Talang Kelapa"},{"id":"1607102","regency_id":"1607","name":"Talang Kelapa"},{"id":"1607112","regency_id":"1607","name":"Rantau Bayur"},{"id":"1607122","regency_id":"1607","name":"Tanjung Lago"},{"id":"1607132","regency_id":"1607","name":"Muara Sugihan"},{"id":"1607142","regency_id":"1607","name":"Air Salek"},{"id":"1607152","regency_id":"1607","name":"Tungkal Ilir"},{"id":"1607162","regency_id":"1607","name":"Suak Tapeh"},{"id":"1607172","regency_id":"1607","name":"Sembawa"},{"id":"1607182","regency_id":"1607","name":"Sumber Marga Telang"},{"id":"1607192","regency_id":"1607","name":"Air Kumbang"},{"id":"1607202","regency_id":"1607","name":"Karangagung Ilir"},{"id":"1607212","regency_id":"1607","name":"Selat Panuguan"}]