[{"id":"1705011","regency_id":"1705","name":"Sukaraja"},{"id":"1705012","regency_id":"1705","name":"Sukaraja"},{"id":"1705021","regency_id":"1705","name":"Seluma"},{"id":"1705031","regency_id":"1705","name":"Talo"},{"id":"1705032","regency_id":"1705","name":"Talo"},{"id":"1705041","regency_id":"1705","name":"Semidang Alas"},{"id":"1705042","regency_id":"1705","name":"Semidang Alas"},{"id":"1705051","regency_id":"1705","name":"Semidang Alas Maras"},{"id":"1705052","regency_id":"1705","name":"Semidang Alas Maras"},{"id":"1705061","regency_id":"1705","name":"Air Periukan"},{"id":"1705062","regency_id":"1705","name":"Air Periukan"},{"id":"1705072","regency_id":"1705","name":"Lubuk Sandi"},{"id":"1705082","regency_id":"1705","name":"Seluma Barat"},{"id":"1705091","regency_id":"1705","name":"Seluma Timur"},{"id":"1705092","regency_id":"1705","name":"Seluma Timur"},{"id":"1705101","regency_id":"1705","name":"Seluma Utara"},{"id":"1705102","regency_id":"1705","name":"Seluma Utara"},{"id":"1705111","regency_id":"1705","name":"Seluma Selatan"},{"id":"1705112","regency_id":"1705","name":"Seluma Selatan"},{"id":"1705122","regency_id":"1705","name":"Talo Kecil"},{"id":"1705132","regency_id":"1705","name":"Ulu Talo"},{"id":"1705142","regency_id":"1705","name":"Ilir Talo"}]