[{"id":"1903011","regency_id":"1903","name":"Toboali"},{"id":"1903012","regency_id":"1903","name":"Toboali"},{"id":"1903022","regency_id":"1903","name":"Lepar Pongok"},{"id":"1903032","regency_id":"1903","name":"Air Gegas"},{"id":"1903042","regency_id":"1903","name":"Simpang Rimba"},{"id":"1903052","regency_id":"1903","name":"Payung"},{"id":"1903062","regency_id":"1903","name":"Tukak Sadai"},{"id":"1903072","regency_id":"1903","name":"Pulaubesar"},{"id":"1903082","regency_id":"1903","name":"Kepulauan Pongok"}]