[{"id":"6210011","regency_id":"6210","name":"Sepang Simin"},{"id":"6210012","regency_id":"6210","name":"Sepang Simin"},{"id":"6210021","regency_id":"6210","name":"Kurun"},{"id":"6210022","regency_id":"6210","name":"Kurun"},{"id":"6210031","regency_id":"6210","name":"Tewah"},{"id":"6210032","regency_id":"6210","name":"Tewah"},{"id":"6210041","regency_id":"6210","name":"Kahayan Hulu Utara"},{"id":"6210042","regency_id":"6210","name":"Kahayan Hulu Utara"},{"id":"6210051","regency_id":"6210","name":"Rungan"},{"id":"6210052","regency_id":"6210","name":"Rungan"},{"id":"6210061","regency_id":"6210","name":"Manuhing"},{"id":"6210062","regency_id":"6210","name":"Manuhing"},{"id":"6210071","regency_id":"6210","name":"Mihing Raya"},{"id":"6210072","regency_id":"6210","name":"Mihing Raya"},{"id":"6210081","regency_id":"6210","name":"Damang Batu"},{"id":"6210082","regency_id":"6210","name":"Damang Batu"},{"id":"6210091","regency_id":"6210","name":"Miri Manasa"},{"id":"6210092","regency_id":"6210","name":"Miri Manasa"},{"id":"6210101","regency_id":"6210","name":"Rungan Hulu"},{"id":"6210102","regency_id":"6210","name":"Rungan Hulu"},{"id":"6210111","regency_id":"6210","name":"Manuhing Raya"},{"id":"6210112","regency_id":"6210","name":"Manuhing Raya"},{"id":"6210121","regency_id":"6210","name":"Rungan Barat"},{"id":"6210122","regency_id":"6210","name":"Rungan Barat"}]