[{"id":"1216072001","district_id":"1216072","postal_code":"22459","name":"Batunajagar"},{"id":"1216072002","district_id":"1216072","postal_code":"22459","name":"Sanggaran I"},{"id":"1216072003","district_id":"1216072","postal_code":"22459","name":"Sitapongan"},{"id":"1216072004","district_id":"1216072","postal_code":"22459","name":"Sigulok"},{"id":"1216072005","district_id":"1216072","postal_code":"22459","name":"Hutaginjang"},{"id":"1216072006","district_id":"1216072","postal_code":"22459","name":"Siborboron"},{"id":"1216072007","district_id":"1216072","postal_code":"22459","name":"Bonan Dolok I"},{"id":"1216072008","district_id":"1216072","postal_code":"22459","name":"Bonan Dolok Ii"},{"id":"1216072009","district_id":"1216072","postal_code":"22459","name":"Sibuntuon"},{"id":"1216072010","district_id":"1216072","postal_code":"22459","name":"Nagurguran"}]