[{"id":"1673051001","district_id":"1673051","postal_code":"31621","name":"Jawa Kanan"},{"id":"1673051002","district_id":"1673051","postal_code":"31621","name":"Jawa Kanan Ss"},{"id":"1673051003","district_id":"1673051","postal_code":"31623","name":"Wira Karya"},{"id":"1673051004","district_id":"1673051","postal_code":"31623","name":"Dempo"},{"id":"1673051005","district_id":"1673051","postal_code":"31622","name":"Jawa Kiri"},{"id":"1673051006","district_id":"1673051","postal_code":"31623","name":"Karya Bakti"},{"id":"1673051007","district_id":"1673051","postal_code":"31624","name":"Mesat Jaya"},{"id":"1673051008","district_id":"1673051","postal_code":"31623","name":"Mesat Seni"},{"id":"1673051009","district_id":"1673051","postal_code":"31623","name":"Cereme Taba"}]