[{"id":"3307152001","district_id":"3307152","postal_code":"56373","name":"Pengarengan"},{"id":"3307152002","district_id":"3307152","postal_code":"56373","name":"Kalikarung"},{"id":"3307152003","district_id":"3307152","postal_code":"56373","name":"Dempel"},{"id":"3307152004","district_id":"3307152","postal_code":"56373","name":"Karangsambung"},{"id":"3307152005","district_id":"3307152","postal_code":"56373","name":"Tempurejo"},{"id":"3307152006","district_id":"3307152","postal_code":"56373","name":"Mergolangu"},{"id":"3307152007","district_id":"3307152","postal_code":"56373","name":"Depok"},{"id":"3307152008","district_id":"3307152","postal_code":"56373","name":"Kalialang"}]