[{"id":"3517162001","district_id":"3517162","postal_code":"61455","name":"Marmoyo"},{"id":"3517162002","district_id":"3517162","postal_code":"61455","name":"Tanjungwadung"},{"id":"3517162003","district_id":"3517162","postal_code":"61455","name":"Mangunan"},{"id":"3517162004","district_id":"3517162","postal_code":"61455","name":"Kabuh"},{"id":"3517162005","district_id":"3517162","postal_code":"61455","name":"Kedungjati"},{"id":"3517162006","district_id":"3517162","postal_code":"61455","name":"Banjardowo"},{"id":"3517162007","district_id":"3517162","postal_code":"61455","name":"Karangpakis"},{"id":"3517162008","district_id":"3517162","postal_code":"61455","name":"Sumberingin"},{"id":"3517162009","district_id":"3517162","postal_code":"61455","name":"Sumbergondang"},{"id":"3517162010","district_id":"3517162","postal_code":"61455","name":"Kauman"},{"id":"3517162011","district_id":"3517162","postal_code":"61455","name":"Munungkerep"},{"id":"3517162012","district_id":"3517162","postal_code":"61455","name":"Genenganjasem"},{"id":"3517162013","district_id":"3517162","postal_code":"61455","name":"Manduro"},{"id":"3517162014","district_id":"3517162","postal_code":"61455","name":"Sukodadi"},{"id":"3517162015","district_id":"3517162","postal_code":"61455","name":"Pengampon"},{"id":"3517162016","district_id":"3517162","postal_code":"61455","name":"Sumberaji"}]