[{"id":"7312012003","district_id":"7312012","postal_code":"90862","name":"Gattareng"},{"id":"7312012004","district_id":"7312012","postal_code":"90862","name":"Watu"},{"id":"7312012005","district_id":"7312012","postal_code":"90862","name":"Goarie"},{"id":"7312012006","district_id":"7312012","postal_code":"90862","name":"Barae"},{"id":"7312012007","district_id":"7312012","postal_code":"90862","name":"Marioriaja"},{"id":"7312012008","district_id":"7312012","postal_code":"90862","name":"Marioritengnga"},{"id":"7312012009","district_id":"7312012","postal_code":"90862","name":"Mariorilau"},{"id":"7312012010","district_id":"7312012","postal_code":"90862","name":"Watu Toa"},{"id":"7312012011","district_id":"7312012","postal_code":"90862","name":"Congko"},{"id":"7312012012","district_id":"7312012","postal_code":"90862","name":"Gattareng Toa"},{"id":"7312012013","district_id":"7312012","postal_code":"90862","name":"Soga"}]