[{"id":"7402042013","district_id":"7402042","postal_code":"93467","name":"Hongoa"},{"id":"7402042016","district_id":"7402042","postal_code":"93467","name":"Mumundowu"},{"id":"7402042019","district_id":"7402042","postal_code":"93467","name":"Ahuawatu"},{"id":"7402042025","district_id":"7402042","postal_code":"93467","name":"Tirawuta"},{"id":"7402042030","district_id":"7402042","postal_code":"93467","name":"Ambulanu"},{"id":"7402042031","district_id":"7402042","postal_code":"93467","name":"Belatu"},{"id":"7402042034","district_id":"7402042","postal_code":"93467","name":"Amesiu"},{"id":"7402042035","district_id":"7402042","postal_code":"93467","name":"Puumbinisi"},{"id":"7402042039","district_id":"7402042","postal_code":"93467","name":"Wawolemo"},{"id":"7402042045","district_id":"7402042","postal_code":"93467","name":"Sulemandara"},{"id":"7402042046","district_id":"7402042","postal_code":"93467","name":"Lalodangge"},{"id":"7402042047","district_id":"7402042","postal_code":"93467","name":"Wawolahumbuti"},{"id":"7402042048","district_id":"7402042","postal_code":"93467","name":"Laloika"},{"id":"7402042049","district_id":"7402042","postal_code":"93467","name":"Lalonggotomi"},{"id":"7402042050","district_id":"7402042","postal_code":"93467","name":"Wonua Mandara"},{"id":"7402042051","district_id":"7402042","postal_code":"93467","name":"Wonua Monapa"},{"id":"7402042052","district_id":"7402042","postal_code":"93467","name":"Lahonggumbi"}]