[{"id":"9206012004","district_id":"9206012","postal_code":"98141","name":"Tuasai"},{"id":"9206012005","district_id":"9206012","postal_code":"98141","name":"Argosigemerai"},{"id":"9206012009","district_id":"9206012","postal_code":"98141","name":"Beimes"},{"id":"9206012010","district_id":"9206012","postal_code":"98141","name":"Iguriji"},{"id":"9206012022","district_id":"9206012","postal_code":"98141","name":"Masina"},{"id":"9206012026","district_id":"9206012","postal_code":"98141","name":"Wesiri"}]