[{"id":"1604012","regency_id":"1604","name":"Tanjungsakti Pumu"},{"id":"1604062","regency_id":"1604","name":"Jarai"},{"id":"1604072","regency_id":"1604","name":"Kota Agung"},{"id":"1604082","regency_id":"1604","name":"Pulaupinang"},{"id":"1604092","regency_id":"1604","name":"Merapi Barat"},{"id":"1604101","regency_id":"1604","name":"Lahat"},{"id":"1604102","regency_id":"1604","name":"Lahat"},{"id":"1604122","regency_id":"1604","name":"Pajar Bulan"},{"id":"1604152","regency_id":"1604","name":"Mulak Ulu"},{"id":"1604162","regency_id":"1604","name":"Kikim Selatan"},{"id":"1604172","regency_id":"1604","name":"Kikim Timur"},{"id":"1604182","regency_id":"1604","name":"Kikim Tengah"},{"id":"1604192","regency_id":"1604","name":"Kikim Barat"},{"id":"1604202","regency_id":"1604","name":"Pseksu"},{"id":"1604212","regency_id":"1604","name":"Gumay Talang"},{"id":"1604222","regency_id":"1604","name":"Pagar Gunung"},{"id":"1604231","regency_id":"1604","name":"Merapi Timur"},{"id":"1604232","regency_id":"1604","name":"Merapi Timur"},{"id":"1604242","regency_id":"1604","name":"Tanjung Sakti Pumi"},{"id":"1604252","regency_id":"1604","name":"Gumay Ulu"},{"id":"1604262","regency_id":"1604","name":"Merapi Selatan"},{"id":"1604272","regency_id":"1604","name":"Tanjungtebat"},{"id":"1604282","regency_id":"1604","name":"Muarapayang"},{"id":"1604292","regency_id":"1604","name":"Sukamerindu"},{"id":"1604302","regency_id":"1604","name":"Mulak Sebingkai"},{"id":"1604312","regency_id":"1604","name":"Lahat Selatan"}]