[{"id":"3214011","regency_id":"3214","name":"Purwakarta"},{"id":"3214012","regency_id":"3214","name":"Purwakarta"},{"id":"3214022","regency_id":"3214","name":"Campaka"},{"id":"3214032","regency_id":"3214","name":"Jatiluhur"},{"id":"3214042","regency_id":"3214","name":"Plered"},{"id":"3214052","regency_id":"3214","name":"Sukatani"},{"id":"3214062","regency_id":"3214","name":"Darangdan"},{"id":"3214072","regency_id":"3214","name":"Maniis"},{"id":"3214082","regency_id":"3214","name":"Tegalwaru"},{"id":"3214092","regency_id":"3214","name":"Wanayasa"},{"id":"3214102","regency_id":"3214","name":"Pasawahan"},{"id":"3214112","regency_id":"3214","name":"Bojong"},{"id":"3214122","regency_id":"3214","name":"Babakancikao"},{"id":"3214132","regency_id":"3214","name":"Bungursari"},{"id":"3214142","regency_id":"3214","name":"Cibatu"},{"id":"3214152","regency_id":"3214","name":"Sukasari"},{"id":"3214162","regency_id":"3214","name":"Pondoksalam"},{"id":"3214172","regency_id":"3214","name":"Kiarapedes"}]