[{"id":"7302011","regency_id":"7302","name":"Gantorang"},{"id":"7302012","regency_id":"7302","name":"Gantorang"},{"id":"7302021","regency_id":"7302","name":"Ujung Bulu"},{"id":"7302031","regency_id":"7302","name":"Bonto Bahari"},{"id":"7302032","regency_id":"7302","name":"Bonto Bahari"},{"id":"7302041","regency_id":"7302","name":"Bonto Tiro"},{"id":"7302042","regency_id":"7302","name":"Bonto Tiro"},{"id":"7302051","regency_id":"7302","name":"Herlang"},{"id":"7302052","regency_id":"7302","name":"Herlang"},{"id":"7302061","regency_id":"7302","name":"Kajang"},{"id":"7302062","regency_id":"7302","name":"Kajang"},{"id":"7302071","regency_id":"7302","name":"Bulukumpa"},{"id":"7302072","regency_id":"7302","name":"Bulukumpa"},{"id":"7302081","regency_id":"7302","name":"Kindang"},{"id":"7302082","regency_id":"7302","name":"Kindang"},{"id":"7302091","regency_id":"7302","name":"Ujungloe"},{"id":"7302092","regency_id":"7302","name":"Ujungloe"},{"id":"7302101","regency_id":"7302","name":"Rilauale"},{"id":"7302102","regency_id":"7302","name":"Rilauale"}]